{
  "sourceUrl": "https://iptv-org.github.io/iptv/index.m3u",
  "mediaUrl": "https://fa723fc1b171.us-west-2.playback.live-video.net/api/video/v1/us-west-2.196233775518.channel.tm5ELzwtPY6t.m3u8",
  "title": "BTB HD (1080p)",
  "contentType": "application/x-mpegurl",
  "duration": -1,
  "groupTitle": "General",
  "tvgId": "BTB.pl",
  "tvgLogo": "https://btb.j00r.us/images/logo_BTB.webp",
  "indexer": "playlist-harvester",
  "skipValidation": true,
  "category": "live_tv",
  "archivedAt": "2026-03-01T11:05:58.339Z"
}