{
  "sourceUrl": "https://iptv-org.github.io/iptv/index.m3u",
  "mediaUrl": "https://stream.esradioecuador.com/hls/stream.m3u8",
  "title": "Gamavisión (720p) [Not 24/7]",
  "contentType": "application/x-mpegurl",
  "duration": -1,
  "groupTitle": "General",
  "tvgId": "Gamavision.ec@SD",
  "tvgLogo": "https://upload.wikimedia.org/wikipedia/commons/9/94/Gamavisi%C3%B3n2018new.png",
  "indexer": "playlist-harvester",
  "skipValidation": true,
  "category": "live_tv",
  "archivedAt": "2026-03-01T11:06:14.364Z"
}