{
  "sourceUrl": "https://iptv-org.github.io/iptv/index.m3u",
  "mediaUrl": "https://chadatv.vedge.infomaniak.com/livecast/chadatv/playlist.m3u8",
  "title": "Chada TV (720p)",
  "contentType": "application/x-mpegurl",
  "duration": -1,
  "groupTitle": "General",
  "tvgId": "ChadaTV.ma@SD",
  "tvgLogo": "https://freebox.cdn.scw.iliad.fr/medium_Logo_chada_tv_2ee1412d38.png",
  "indexer": "playlist-harvester",
  "skipValidation": true,
  "category": "live_tv",
  "archivedAt": "2026-03-01T11:06:03.179Z"
}