{
  "sourceUrl": "https://iptv-org.github.io/iptv/index.m3u",
  "mediaUrl": "https://6n3yowknl9ok-hls-live.5centscdn.com/HMN/271ddf829afeece44d8732757fba1a66.sdp/playlist.m3u8",
  "title": "Health Media TV (720p)",
  "contentType": "application/x-mpegurl",
  "duration": -1,
  "groupTitle": "Lifestyle",
  "tvgId": "HealthMediaTV.us@SD",
  "tvgLogo": "https://i.imgur.com/x3lIyG9.png",
  "indexer": "playlist-harvester",
  "skipValidation": true,
  "category": "live_tv",
  "archivedAt": "2026-03-01T11:06:17.241Z"
}