{
  "sourceUrl": "https://iptv-org.github.io/iptv/index.m3u",
  "mediaUrl": "https://host.streamingnation.live:3940/live/caobatvlive.m3u8",
  "title": "Caoba TV Radio (720p) [Not 24/7]",
  "contentType": "application/x-mpegurl",
  "duration": -1,
  "groupTitle": "General",
  "tvgId": "CaobaTVRadio.do@HD",
  "tvgLogo": "https://www.vivalivetv.com/public/files/shows/0/1/3906-294x165-FFFFFF.jpg",
  "indexer": "playlist-harvester",
  "skipValidation": true,
  "category": "live_tv",
  "archivedAt": "2026-03-01T11:06:01.563Z"
}