{
  "sourceUrl": "https://iptv-org.github.io/iptv/index.m3u",
  "mediaUrl": "https://stream.livenewsplay.com:9443/hls/cnbc/cnbcsd.m3u8",
  "title": "CNBC (720p)",
  "contentType": "application/x-mpegurl",
  "duration": -1,
  "groupTitle": "Business",
  "tvgId": "CNBC.us@SD",
  "tvgLogo": "https://upload.wikimedia.org/wikipedia/commons/thumb/b/bc/CNBC_2025.svg/512px-CNBC_2025.svg.png",
  "indexer": "playlist-harvester",
  "skipValidation": true,
  "category": "live_tv",
  "archivedAt": "2026-03-01T11:06:04.684Z"
}