{
  "sourceUrl": "https://iptv-org.github.io/iptv/index.m3u",
  "mediaUrl": "https://live.artidijitalmedya.com/artidijital_trakyaturk/trakyaturk/playlist.m3u8",
  "title": "Trakya Türk TV (720p)",
  "contentType": "application/x-mpegurl",
  "duration": -1,
  "groupTitle": "General",
  "tvgId": "TrakyaTurk.tr@SD",
  "tvgLogo": "https://trakyaturktv.com/uploads/library/2024/04/unnamed1.jpg",
  "indexer": "playlist-harvester",
  "skipValidation": true,
  "category": "live_tv",
  "archivedAt": "2026-03-01T11:07:06.276Z"
}