{
  "sourceUrl": "https://iptv-org.github.io/iptv/index.m3u",
  "mediaUrl": "https://5926fc9c7c5b2.streamlock.net/9040/9040/chunklist_w1373908906.m3u8",
  "title": "Onda TV (568p)",
  "contentType": "application/x-mpegurl",
  "duration": -1,
  "groupTitle": "General",
  "tvgId": "OndaTV.it@SD",
  "tvgLogo": "https://upload.wikimedia.org/wikipedia/it/thumb/9/99/Ondatv.jpg/512px-Ondatv.jpg",
  "indexer": "playlist-harvester",
  "skipValidation": true,
  "category": "live_tv",
  "archivedAt": "2026-03-01T11:06:39.394Z"
}